[
  { "id": "deceptive", "title": "Deceptive", "wrong": "Induces or exploits a false belief about a material fact.", "operatesOn": "Beliefs (epistemic)", "needsIntent": "No", "example": "Hidden odds; disguised ads; value obfuscation.", "references": ["mathur-2021", "sobel-2020", "gray-2018"] },
  { "id": "manipulative", "title": "Manipulative", "wrong": "Bypasses or subverts rational agency via bias, emotion, or hidden influence.", "operatesOn": "The decision process", "needsIntent": "Usually covert", "example": "Near-miss; variable-ratio rewards; confirmshaming.", "references": ["wilkinson-2013", "ahuja-2022", "sanchezchamorro-2023"] },
  { "id": "coercive", "title": "Coercive", "wrong": "Removes, withholds, or penalises acceptable alternatives; applies pressure.", "operatesOn": "The choice set / freedom", "needsIntent": "No (effect-based)", "example": "Forced action; obstructed exit; withholding progression to compel pay; play-by-appointment.", "references": ["goltz-2020", "mathur-2019", "nguyen-2020"] },
  { "id": "exploitative", "title": "Exploitative", "wrong": "Takes unfair advantage of an asymmetry or vulnerability for the provider's gain — even if the user is not deceived.", "operatesOn": "Fairness / autonomy / vulnerability", "needsIntent": "No (effect-based)", "example": "Loot boxes; whale-targeting; engineered grind; SES-targeted monetisation.", "references": ["brenncke-2023", "helberger-2021", "king-delfabbro-2019", "strycharz-2021"] },
  { "id": "malicious", "title": "Malicious", "wrong": "Design deliberately built or deployed to work against the user's interest.", "operatesOn": "Intent + effect", "needsIntent": "Yes (intent-laden)", "example": "Patented spend-maximisation; covert data capture; 'malicious interface design'.", "references": ["conti-2010", "schafer-2024a", "mildner-2023"] }
]
